README.rst
pyproject.toml
setup.py
stable_rt_tools/__init__.py
stable_rt_tools/about.py
stable_rt_tools/srt.py
stable_rt_tools/srt_announce.py
stable_rt_tools/srt_commit.py
stable_rt_tools/srt_create.py
stable_rt_tools/srt_git_filter.py
stable_rt_tools/srt_push.py
stable_rt_tools/srt_sign.py
stable_rt_tools/srt_tag.py
stable_rt_tools/srt_upload.py
stable_rt_tools/srt_util.py
stable_rt_tools/srt_util_context.py
stable_rt_tools/srt_util_tag.py
stable_rt_tools.egg-info/PKG-INFO
stable_rt_tools.egg-info/SOURCES.txt
stable_rt_tools.egg-info/dependency_links.txt
stable_rt_tools.egg-info/entry_points.txt
stable_rt_tools.egg-info/requires.txt
stable_rt_tools.egg-info/top_level.txt
stable_rt_tools/tests/__init__.py
stable_rt_tools/tests/test_srt.py
stable_rt_tools/tests/test_srt_util.py
stable_rt_tools/tests/test_srt_util_context.py
stable_rt_tools/tests/test_srt_util_tag.py